[
    {
        "Edicao": "STARTER DECK -Yamato- [ST-09]",
        "Nome": "Yamato",
        "Nome_Base": "Yamato",
        "Codigo": "ST09-001",
        "Raridade": "L",
        "Tipo": "LEADER",
        "Variante": 0,
        "Imagem_URL": "https://en.onepiece-cardgame.com/images/cardlist/card/ST09-001.png?251031",
        "Cost": "",
        "Attribute": "Strike",
        "Power": "5000",
        "Counter": "-",
        "Color": "Yellow",
        "Block_icon": "",
        "Type_Card": "Land of Wano",
        "Trigger": "",
        "Effect": "[DON!! x1] [Opponent's Turn] If you have 2 or less Life cards, this Leader gains +1000 power.",
        "Card_Set": "-Yamato-[ST-09]",
        "Imagem_Arquivo": "imagens\\STARTER DECK -Yamato- [ST-09]\\ST09-001.jpg"
    },
    {
        "Edicao": "STARTER DECK -Yamato- [ST-09]",
        "Nome": "Uzuki Tempura",
        "Nome_Base": "Uzuki Tempura",
        "Codigo": "ST09-002",
        "Raridade": "C",
        "Tipo": "CHARACTER",
        "Variante": 0,
        "Imagem_URL": "https://en.onepiece-cardgame.com/images/cardlist/card/ST09-002.png?251031",
        "Cost": "4",
        "Attribute": "Slash",
        "Power": "5000",
        "Counter": "1000",
        "Color": "Yellow",
        "Block_icon": "",
        "Type_Card": "Land of Wano",
        "Trigger": "[Trigger] Rest up to 1 of your opponent's Characters with a cost of 2 or less and add this card to your hand.",
        "Effect": "-",
        "Card_Set": "-Yamato-[ST-09]",
        "Imagem_Arquivo": "imagens\\STARTER DECK -Yamato- [ST-09]\\ST09-002.jpg"
    },
    {
        "Edicao": "STARTER DECK -Yamato- [ST-09]",
        "Nome": "Ulti",
        "Nome_Base": "Ulti",
        "Codigo": "ST09-003",
        "Raridade": "C",
        "Tipo": "CHARACTER",
        "Variante": 0,
        "Imagem_URL": "https://en.onepiece-cardgame.com/images/cardlist/card/ST09-003.png?251031",
        "Cost": "4",
        "Attribute": "Strike",
        "Power": "6000",
        "Counter": "1000",
        "Color": "Yellow",
        "Block_icon": "",
        "Type_Card": "Animal Kingdom Pirates",
        "Trigger": "",
        "Effect": "-",
        "Card_Set": "-Yamato-[ST-09]",
        "Imagem_Arquivo": "imagens\\STARTER DECK -Yamato- [ST-09]\\ST09-003.jpg"
    },
    {
        "Edicao": "STARTER DECK -Yamato- [ST-09]",
        "Nome": "Kaido",
        "Nome_Base": "Kaido",
        "Codigo": "ST09-004",
        "Raridade": "C",
        "Tipo": "CHARACTER",
        "Variante": 0,
        "Imagem_URL": "https://en.onepiece-cardgame.com/images/cardlist/card/ST09-004.png?251031",
        "Cost": "4",
        "Attribute": "Special",
        "Power": "5000",
        "Counter": "1000",
        "Color": "Yellow",
        "Block_icon": "",
        "Type_Card": "The Four Emperors/Animal Kingdom Pirates",
        "Trigger": "",
        "Effect": "[DON!! x1] If you have 2 or less Life cards, this Character cannot be K.O.'d in battle.",
        "Card_Set": "-Yamato-[ST-09]",
        "Imagem_Arquivo": "imagens\\STARTER DECK -Yamato- [ST-09]\\ST09-004.jpg"
    },
    {
        "Edicao": "STARTER DECK -Yamato- [ST-09]",
        "Nome": "Kouzuki Oden",
        "Nome_Base": "Kouzuki Oden",
        "Codigo": "ST09-005",
        "Raridade": "SR",
        "Tipo": "CHARACTER",
        "Variante": 0,
        "Imagem_URL": "https://en.onepiece-cardgame.com/images/cardlist/card/ST09-005.png?251031",
        "Cost": "7",
        "Attribute": "Slash",
        "Power": "7000",
        "Counter": "-",
        "Color": "Yellow",
        "Block_icon": "",
        "Type_Card": "Land of Wano/Kouzuki Clan",
        "Trigger": "",
        "Effect": "[DON!! x1] This Character gains [Double Attack].\n(This card deals 2 damage.)\n[On K.O.] You may trash 2 cards from your hand: Add up to 1 card from the top of your deck to the top of your Life cards.",
        "Card_Set": "-Yamato-[ST-09]",
        "Imagem_Arquivo": "imagens\\STARTER DECK -Yamato- [ST-09]\\ST09-005.jpg"
    },
    {
        "Edicao": "STARTER DECK -Yamato- [ST-09]",
        "Nome": "Kouzuki Momonosuke",
        "Nome_Base": "Kouzuki Momonosuke",
        "Codigo": "ST09-006",
        "Raridade": "C",
        "Tipo": "CHARACTER",
        "Variante": 0,
        "Imagem_URL": "https://en.onepiece-cardgame.com/images/cardlist/card/ST09-006.png?251031",
        "Cost": "2",
        "Attribute": "Special",
        "Power": "4000",
        "Counter": "1000",
        "Color": "Yellow",
        "Block_icon": "",
        "Type_Card": "Land of Wano/Kouzuki Clan",
        "Trigger": "",
        "Effect": "-",
        "Card_Set": "-Yamato-[ST-09]",
        "Imagem_Arquivo": "imagens\\STARTER DECK -Yamato- [ST-09]\\ST09-006.jpg"
    },
    {
        "Edicao": "STARTER DECK -Yamato- [ST-09]",
        "Nome": "Shinobu",
        "Nome_Base": "Shinobu",
        "Codigo": "ST09-007",
        "Raridade": "C",
        "Tipo": "CHARACTER",
        "Variante": 0,
        "Imagem_URL": "https://en.onepiece-cardgame.com/images/cardlist/card/ST09-007.png?251031",
        "Cost": "3",
        "Attribute": "Special",
        "Power": "2000",
        "Counter": "-",
        "Color": "Yellow",
        "Block_icon": "",
        "Type_Card": "Land of Wano",
        "Trigger": "",
        "Effect": "[Blocker] (After your opponent declares an attack, you may rest this card to make it the new target of the attack.)\n[On Block] You may add 1 card from the top or bottom of your Life cards to your hand: This Character gains +4000 power during this battle.",
        "Card_Set": "-Yamato-[ST-09]",
        "Imagem_Arquivo": "imagens\\STARTER DECK -Yamato- [ST-09]\\ST09-007.jpg"
    },
    {
        "Edicao": "STARTER DECK -Yamato- [ST-09]",
        "Nome": "Shimotsuki Ushimaru",
        "Nome_Base": "Shimotsuki Ushimaru",
        "Codigo": "ST09-008",
        "Raridade": "C",
        "Tipo": "CHARACTER",
        "Variante": 0,
        "Imagem_URL": "https://en.onepiece-cardgame.com/images/cardlist/card/ST09-008.png?251031",
        "Cost": "5",
        "Attribute": "Slash",
        "Power": "6000",
        "Counter": "-",
        "Color": "Yellow",
        "Block_icon": "",
        "Type_Card": "Land of Wano",
        "Trigger": "",
        "Effect": "[DON!! x1] [When Attacking] You may add 1 card from the top or bottom of your Life cards to your hand: Play up to 1 yellow {Land of Wano} type Character card with a cost of 4 or less from your hand.",
        "Card_Set": "-Yamato-[ST-09]",
        "Imagem_Arquivo": "imagens\\STARTER DECK -Yamato- [ST-09]\\ST09-008.jpg"
    },
    {
        "Edicao": "STARTER DECK -Yamato- [ST-09]",
        "Nome": "Fugetsu Omusubi",
        "Nome_Base": "Fugetsu Omusubi",
        "Codigo": "ST09-009",
        "Raridade": "C",
        "Tipo": "CHARACTER",
        "Variante": 0,
        "Imagem_URL": "https://en.onepiece-cardgame.com/images/cardlist/card/ST09-009.png?251031",
        "Cost": "3",
        "Attribute": "Slash",
        "Power": "4000",
        "Counter": "1000",
        "Color": "Yellow",
        "Block_icon": "",
        "Type_Card": "Land of Wano",
        "Trigger": "[Trigger] K.O. up to 1 of your opponent's Characters with a cost of 1 or less and add this card to your hand.",
        "Effect": "-",
        "Card_Set": "-Yamato-[ST-09]",
        "Imagem_Arquivo": "imagens\\STARTER DECK -Yamato- [ST-09]\\ST09-009.jpg"
    },
    {
        "Edicao": "STARTER DECK -Yamato- [ST-09]",
        "Nome": "Portgas.D.Ace",
        "Nome_Base": "Portgas.D.Ace",
        "Codigo": "ST09-010",
        "Raridade": "SR",
        "Tipo": "CHARACTER",
        "Variante": 0,
        "Imagem_URL": "https://en.onepiece-cardgame.com/images/cardlist/card/ST09-010.png?251031",
        "Cost": "6",
        "Attribute": "Special",
        "Power": "7000",
        "Counter": "-",
        "Color": "Yellow",
        "Block_icon": "",
        "Type_Card": "Land of Wano/Whitebeard Pirates",
        "Trigger": "",
        "Effect": "[Once Per Turn] If this Character would be K.O.'d, you may trash 1 card from the top or bottom of your Life cards instead.",
        "Card_Set": "-Yamato-[ST-09]",
        "Imagem_Arquivo": "imagens\\STARTER DECK -Yamato- [ST-09]\\ST09-010.jpg"
    },
    {
        "Edicao": "STARTER DECK -Yamato- [ST-09]",
        "Nome": "Monkey.D.Luffy",
        "Nome_Base": "Monkey.D.Luffy",
        "Codigo": "ST09-011",
        "Raridade": "C",
        "Tipo": "CHARACTER",
        "Variante": 0,
        "Imagem_URL": "https://en.onepiece-cardgame.com/images/cardlist/card/ST09-011.png?251031",
        "Cost": "3",
        "Attribute": "Strike",
        "Power": "5000",
        "Counter": "1000",
        "Color": "Yellow",
        "Block_icon": "",
        "Type_Card": "Land of Wano/Straw Hat Crew",
        "Trigger": "",
        "Effect": "-",
        "Card_Set": "-Yamato-[ST-09]",
        "Imagem_Arquivo": "imagens\\STARTER DECK -Yamato- [ST-09]\\ST09-011.jpg"
    },
    {
        "Edicao": "STARTER DECK -Yamato- [ST-09]",
        "Nome": "Yamato",
        "Nome_Base": "Yamato",
        "Codigo": "ST09-012",
        "Raridade": "C",
        "Tipo": "CHARACTER",
        "Variante": 0,
        "Imagem_URL": "https://en.onepiece-cardgame.com/images/cardlist/card/ST09-012.png?251031",
        "Cost": "3",
        "Attribute": "Strike",
        "Power": "3000",
        "Counter": "2000",
        "Color": "Yellow",
        "Block_icon": "",
        "Type_Card": "Land of Wano",
        "Trigger": "",
        "Effect": "[When Attacking] You may add 1 card from the top or bottom of your Life cards to your hand: This Character gains +2000 power until the start of your next turn.",
        "Card_Set": "-Yamato-[ST-09]",
        "Imagem_Arquivo": "imagens\\STARTER DECK -Yamato- [ST-09]\\ST09-012.jpg"
    },
    {
        "Edicao": "STARTER DECK -Yamato- [ST-09]",
        "Nome": "Yamato",
        "Nome_Base": "Yamato",
        "Codigo": "ST09-013",
        "Raridade": "C",
        "Tipo": "CHARACTER",
        "Variante": 0,
        "Imagem_URL": "https://en.onepiece-cardgame.com/images/cardlist/card/ST09-013.png?251031",
        "Cost": "5",
        "Attribute": "Special",
        "Power": "7000",
        "Counter": "1000",
        "Color": "Yellow",
        "Block_icon": "",
        "Type_Card": "Land of Wano",
        "Trigger": "",
        "Effect": "-",
        "Card_Set": "-Yamato-[ST-09]",
        "Imagem_Arquivo": "imagens\\STARTER DECK -Yamato- [ST-09]\\ST09-013.jpg"
    },
    {
        "Edicao": "STARTER DECK -Yamato- [ST-09]",
        "Nome": "Narikabura Arrow",
        "Nome_Base": "Narikabura Arrow",
        "Codigo": "ST09-014",
        "Raridade": "C",
        "Tipo": "EVENT",
        "Variante": 0,
        "Imagem_URL": "https://en.onepiece-cardgame.com/images/cardlist/card/ST09-014.png?251031",
        "Cost": "1",
        "Attribute": "-",
        "Power": "-",
        "Counter": "-",
        "Color": "Yellow",
        "Block_icon": "",
        "Type_Card": "Land of Wano",
        "Trigger": "[Trigger] You may trash 2 cards from your hand: Add up to 1 card from the top of your deck to the top of your Life cards.",
        "Effect": "[Counter] If you have 2 or less Life cards, give up to 1 of your opponent's Leader or Character cards −3000 power during this turn.",
        "Card_Set": "-Yamato-[ST-09]",
        "Imagem_Arquivo": "imagens\\STARTER DECK -Yamato- [ST-09]\\ST09-014.jpg"
    },
    {
        "Edicao": "STARTER DECK -Yamato- [ST-09]",
        "Nome": "Thunder Bagua",
        "Nome_Base": "Thunder Bagua",
        "Codigo": "ST09-015",
        "Raridade": "C",
        "Tipo": "EVENT",
        "Variante": 0,
        "Imagem_URL": "https://en.onepiece-cardgame.com/images/cardlist/card/ST09-015.png?251031",
        "Cost": "2",
        "Attribute": "-",
        "Power": "-",
        "Counter": "-",
        "Color": "Yellow",
        "Block_icon": "",
        "Type_Card": "Land of Wano",
        "Trigger": "[Trigger] Draw 1 card.",
        "Effect": "[Counter] Up to 1 of your Leader or Character cards gains +4000 power during this battle. Then, if you have 2 or less Life cards, add up to 1 of your opponent's Characters with a cost of 3 or less to the top or bottom of the owner's Life cards face-up.",
        "Card_Set": "-Yamato-[ST-09]",
        "Imagem_Arquivo": "imagens\\STARTER DECK -Yamato- [ST-09]\\ST09-015.jpg"
    }
]